<?xml version="1.0" encoding="utf-8"?><text name="Статья 43. Содержание общего имущества в коммунальной квартире" parent="1923" id="1931"><tags></tags><paragraphs><paragraph id="16054"><sentence id="48257"><source>Статья 43.</source><tokens><token text="Статья" id="872996"><tfr t="Статья" rev_id="1752525"><v><l t="статья" id="335173"><g v="NOUN"></g><g v="inan"></g><g v="femn"></g><g v="sing"></g><g v="nomn"></g></l></v></tfr></token><token text="43" id="872997"><tfr t="43" rev_id="2466521"><v><l t="43" id="0"><g v="NUMB"></g></l></v></tfr></token><token text="." id="872998"><tfr t="." rev_id="1752527"><v><l t="." id="0"><g v="PNCT"></g></l></v></tfr></token></tokens></sentence><sentence id="48258"><source>Содержание общего имущества в коммунальной квартире</source><tokens><token text="Содержание" id="872999"><tfr t="Содержание" rev_id="1752528"><v><l t="содержание" id="328404"><g v="NOUN"></g><g v="inan"></g><g v="neut"></g><g v="sing"></g><g v="nomn"></g></l></v><v><l t="содержание" id="328404"><g v="NOUN"></g><g v="inan"></g><g v="neut"></g><g v="sing"></g><g v="accs"></g></l></v></tfr></token><token text="общего" id="873000"><tfr t="общего" rev_id="3544739"><v><l t="общий" id="201663"><g v="ADJF"></g><g v="neut"></g><g v="sing"></g><g v="gent"></g></l></v></tfr></token><token text="имущества" id="873001"><tfr t="имущества" rev_id="3528761"><v><l t="имущество" id="121943"><g v="NOUN"></g><g v="inan"></g><g v="neut"></g><g v="sing"></g><g v="gent"></g></l></v></tfr></token><token text="в" id="873002"><tfr t="в" rev_id="1752531"><v><l t="в" id="37409"><g v="PREP"></g></l></v></tfr></token><token text="коммунальной" id="873003"><tfr t="коммунальной" rev_id="4421309"><v><l t="коммунальный" id="137032"><g v="ADJF"></g><g v="femn"></g><g v="sing"></g><g v="loct"></g></l></v></tfr></token><token text="квартире" id="873004"><tfr t="квартире" rev_id="3646406"><v><l t="квартира" id="132025"><g v="NOUN"></g><g v="inan"></g><g v="femn"></g><g v="sing"></g><g v="loct"></g></l></v></tfr></token></tokens></sentence></paragraph><paragraph id="16055"><sentence id="48259"><source>1. Собственники комнат в коммунальной квартире несут бремя расходов на содержание общего имущества в данной квартире.</source><tokens><token text="1" id="873005"><tfr t="1" rev_id="2466522"><v><l t="1" id="0"><g v="NUMB"></g></l></v></tfr></token><token text="." id="873006"><tfr t="." rev_id="1752535"><v><l t="." id="0"><g v="PNCT"></g></l></v></tfr></token><token text="Собственники" id="873007"><tfr t="Собственники" rev_id="1752536"><v><l t="собственник" id="327827"><g v="NOUN"></g><g v="anim"></g><g v="masc"></g><g v="plur"></g><g v="nomn"></g></l></v></tfr></token><token text="комнат" id="873008"><tfr t="комнат" rev_id="1752537"><v><l t="комната" id="137100"><g v="NOUN"></g><g v="inan"></g><g v="femn"></g><g v="plur"></g><g v="gent"></g></l></v></tfr></token><token text="в" id="873009"><tfr t="в" rev_id="1752538"><v><l t="в" id="37409"><g v="PREP"></g></l></v></tfr></token><token text="коммунальной" id="873010"><tfr t="коммунальной" rev_id="4419503"><v><l t="коммунальный" id="137032"><g v="ADJF"></g><g v="femn"></g><g v="sing"></g><g v="loct"></g></l></v></tfr></token><token text="квартире" id="873011"><tfr t="квартире" rev_id="3644807"><v><l t="квартира" id="132025"><g v="NOUN"></g><g v="inan"></g><g v="femn"></g><g v="sing"></g><g v="loct"></g></l></v></tfr></token><token text="несут" id="873012"><tfr t="несут" rev_id="1752541"><v><l t="несу" id="188677"><g v="VERB"></g><g v="impf"></g><g v="tran"></g><g v="plur"></g><g v="3per"></g><g v="pres"></g><g v="indc"></g></l></v></tfr></token><token text="бремя" id="873013"><tfr t="бремя" rev_id="1752542"><v><l t="бремя" id="33839"><g v="NOUN"></g><g v="inan"></g><g v="neut"></g><g v="sing"></g><g v="nomn"></g></l></v><v><l t="бремя" id="33839"><g v="NOUN"></g><g v="inan"></g><g v="neut"></g><g v="sing"></g><g v="accs"></g></l></v></tfr></token><token text="расходов" id="873014"><tfr t="расходов" rev_id="1752543"><v><l t="расход" id="303036"><g v="NOUN"></g><g v="inan"></g><g v="masc"></g><g v="plur"></g><g v="gent"></g></l></v></tfr></token><token text="на" id="873015"><tfr t="на" rev_id="3342910"><v><l t="на" id="166264"><g v="PREP"></g></l></v></tfr></token><token text="содержание" id="873016"><tfr t="содержание" rev_id="1752545"><v><l t="содержание" id="328404"><g v="NOUN"></g><g v="inan"></g><g v="neut"></g><g v="sing"></g><g v="nomn"></g></l></v><v><l t="содержание" id="328404"><g v="NOUN"></g><g v="inan"></g><g v="neut"></g><g v="sing"></g><g v="accs"></g></l></v></tfr></token><token text="общего" id="873017"><tfr t="общего" rev_id="4210047"><v><l t="общий" id="201663"><g v="ADJF"></g><g v="neut"></g><g v="sing"></g><g v="gent"></g></l></v></tfr></token><token text="имущества" id="873018"><tfr t="имущества" rev_id="3529281"><v><l t="имущество" id="121943"><g v="NOUN"></g><g v="inan"></g><g v="neut"></g><g v="sing"></g><g v="gent"></g></l></v></tfr></token><token text="в" id="873019"><tfr t="в" rev_id="1752548"><v><l t="в" id="37409"><g v="PREP"></g></l></v></tfr></token><token text="данной" id="873020"><tfr t="данной" rev_id="3663296"><v><l t="данна" id="78298"><g v="NOUN"></g><g v="anim"></g><g v="femn"></g><g v="Name"></g><g v="sing"></g><g v="ablt"></g></l></v><v><l t="данный" id="78303"><g v="ADJF"></g><g v="Apro"></g><g v="femn"></g><g v="sing"></g><g v="gent"></g></l></v><v><l t="данный" id="78303"><g v="ADJF"></g><g v="Apro"></g><g v="femn"></g><g v="sing"></g><g v="datv"></g></l></v><v><l t="данный" id="78303"><g v="ADJF"></g><g v="Apro"></g><g v="femn"></g><g v="sing"></g><g v="ablt"></g></l></v><v><l t="данный" id="78303"><g v="ADJF"></g><g v="Apro"></g><g v="femn"></g><g v="sing"></g><g v="loct"></g></l></v><v><l t="данный" id="78549"><g v="PRTF"></g><g v="perf"></g><g v="tran"></g><g v="past"></g><g v="pssv"></g><g v="femn"></g><g v="sing"></g><g v="gent"></g></l></v><v><l t="данный" id="78549"><g v="PRTF"></g><g v="perf"></g><g v="tran"></g><g v="past"></g><g v="pssv"></g><g v="femn"></g><g v="sing"></g><g v="datv"></g></l></v><v><l t="данный" id="78549"><g v="PRTF"></g><g v="perf"></g><g v="tran"></g><g v="past"></g><g v="pssv"></g><g v="femn"></g><g v="sing"></g><g v="ablt"></g></l></v><v><l t="данный" id="78549"><g v="PRTF"></g><g v="perf"></g><g v="tran"></g><g v="past"></g><g v="pssv"></g><g v="femn"></g><g v="sing"></g><g v="loct"></g></l></v></tfr></token><token text="квартире" id="873021"><tfr t="квартире" rev_id="3647517"><v><l t="квартира" id="132025"><g v="NOUN"></g><g v="inan"></g><g v="femn"></g><g v="sing"></g><g v="loct"></g></l></v></tfr></token><token text="." id="873022"><tfr t="." rev_id="1752551"><v><l t="." id="0"><g v="PNCT"></g></l></v></tfr></token></tokens></sentence></paragraph><paragraph id="16056"><sentence id="48260"><source>2. Доля обязательных расходов на содержание общего имущества в коммунальной квартире, бремя которых несет собственник комнаты в данной квартире, определяется долей в праве общей собственности на общее имущество в данной квартире указанного собственника.</source><tokens><token text="2" id="873023"><tfr t="2" rev_id="2466523"><v><l t="2" id="0"><g v="NUMB"></g></l></v></tfr></token><token text="." id="873024"><tfr t="." rev_id="1752553"><v><l t="." id="0"><g v="PNCT"></g></l></v></tfr></token><token text="Доля" id="873025"><tfr t="Доля" rev_id="1752554"><v><l t="доля" id="88151"><g v="NOUN"></g><g v="inan"></g><g v="femn"></g><g v="sing"></g><g v="nomn"></g></l></v></tfr></token><token text="обязательных" id="873026"><tfr t="обязательных" rev_id="4370771"><v><l t="обязательный" id="202087"><g v="ADJF"></g><g v="plur"></g><g v="gent"></g></l></v></tfr></token><token text="расходов" id="873027"><tfr t="расходов" rev_id="1752556"><v><l t="расход" id="303036"><g v="NOUN"></g><g v="inan"></g><g v="masc"></g><g v="plur"></g><g v="gent"></g></l></v></tfr></token><token text="на" id="873028"><tfr t="на" rev_id="3396088"><v><l t="на" id="166264"><g v="PREP"></g></l></v></tfr></token><token text="содержание" id="873029"><tfr t="содержание" rev_id="3673071"><v><l t="содержание" id="328404"><g v="NOUN"></g><g v="inan"></g><g v="neut"></g><g v="sing"></g><g v="accs"></g></l></v></tfr></token><token text="общего" id="873030"><tfr t="общего" rev_id="4207527"><v><l t="общий" id="201663"><g v="ADJF"></g><g v="neut"></g><g v="sing"></g><g v="gent"></g></l></v></tfr></token><token text="имущества" id="873031"><tfr t="имущества" rev_id="3529090"><v><l t="имущество" id="121943"><g v="NOUN"></g><g v="inan"></g><g v="neut"></g><g v="sing"></g><g v="gent"></g></l></v></tfr></token><token text="в" id="873032"><tfr t="в" rev_id="1752561"><v><l t="в" id="37409"><g v="PREP"></g></l></v></tfr></token><token text="коммунальной" id="873033"><tfr t="коммунальной" rev_id="4419054"><v><l t="коммунальный" id="137032"><g v="ADJF"></g><g v="femn"></g><g v="sing"></g><g v="loct"></g></l></v></tfr></token><token text="квартире" id="873034"><tfr t="квартире" rev_id="3645433"><v><l t="квартира" id="132025"><g v="NOUN"></g><g v="inan"></g><g v="femn"></g><g v="sing"></g><g v="loct"></g></l></v></tfr></token><token text="," id="873035"><tfr t="," rev_id="1752564"><v><l t="," id="0"><g v="PNCT"></g></l></v></tfr></token><token text="бремя" id="873036"><tfr t="бремя" rev_id="1752565"><v><l t="бремя" id="33839"><g v="NOUN"></g><g v="inan"></g><g v="neut"></g><g v="sing"></g><g v="nomn"></g></l></v><v><l t="бремя" id="33839"><g v="NOUN"></g><g v="inan"></g><g v="neut"></g><g v="sing"></g><g v="accs"></g></l></v></tfr></token><token text="которых" id="873037"><tfr t="которых" rev_id="4369522"><v><l t="который" id="141203"><g v="ADJF"></g><g v="Apro"></g><g v="Subx"></g><g v="Anph"></g><g v="plur"></g><g v="gent"></g></l></v></tfr></token><token text="несет" id="873038"><tfr t="несет" rev_id="1752567"><v><l t="несу" id="188677"><g v="VERB"></g><g v="impf"></g><g v="tran"></g><g v="sing"></g><g v="3per"></g><g v="pres"></g><g v="indc"></g></l></v></tfr></token><token text="собственник" id="873039"><tfr t="собственник" rev_id="1752568"><v><l t="собственник" id="327827"><g v="NOUN"></g><g v="anim"></g><g v="masc"></g><g v="sing"></g><g v="nomn"></g></l></v></tfr></token><token text="комнаты" id="873040"><tfr t="комнаты" rev_id="3528375"><v><l t="комната" id="137100"><g v="NOUN"></g><g v="inan"></g><g v="femn"></g><g v="sing"></g><g v="gent"></g></l></v></tfr></token><token text="в" id="873041"><tfr t="в" rev_id="1752570"><v><l t="в" id="37409"><g v="PREP"></g></l></v></tfr></token><token text="данной" id="873042"><tfr t="данной" rev_id="3663297"><v><l t="данна" id="78298"><g v="NOUN"></g><g v="anim"></g><g v="femn"></g><g v="Name"></g><g v="sing"></g><g v="ablt"></g></l></v><v><l t="данный" id="78303"><g v="ADJF"></g><g v="Apro"></g><g v="femn"></g><g v="sing"></g><g v="gent"></g></l></v><v><l t="данный" id="78303"><g v="ADJF"></g><g v="Apro"></g><g v="femn"></g><g v="sing"></g><g v="datv"></g></l></v><v><l t="данный" id="78303"><g v="ADJF"></g><g v="Apro"></g><g v="femn"></g><g v="sing"></g><g v="ablt"></g></l></v><v><l t="данный" id="78303"><g v="ADJF"></g><g v="Apro"></g><g v="femn"></g><g v="sing"></g><g v="loct"></g></l></v><v><l t="данный" id="78549"><g v="PRTF"></g><g v="perf"></g><g v="tran"></g><g v="past"></g><g v="pssv"></g><g v="femn"></g><g v="sing"></g><g v="gent"></g></l></v><v><l t="данный" id="78549"><g v="PRTF"></g><g v="perf"></g><g v="tran"></g><g v="past"></g><g v="pssv"></g><g v="femn"></g><g v="sing"></g><g v="datv"></g></l></v><v><l t="данный" id="78549"><g v="PRTF"></g><g v="perf"></g><g v="tran"></g><g v="past"></g><g v="pssv"></g><g v="femn"></g><g v="sing"></g><g v="ablt"></g></l></v><v><l t="данный" id="78549"><g v="PRTF"></g><g v="perf"></g><g v="tran"></g><g v="past"></g><g v="pssv"></g><g v="femn"></g><g v="sing"></g><g v="loct"></g></l></v></tfr></token><token text="квартире" id="873043"><tfr t="квартире" rev_id="3645513"><v><l t="квартира" id="132025"><g v="NOUN"></g><g v="inan"></g><g v="femn"></g><g v="sing"></g><g v="loct"></g></l></v></tfr></token><token text="," id="873044"><tfr t="," rev_id="1752573"><v><l t="," id="0"><g v="PNCT"></g></l></v></tfr></token><token text="определяется" id="873045"><tfr t="определяется" rev_id="1752574"><v><l t="определяюсь" id="208019"><g v="VERB"></g><g v="impf"></g><g v="intr"></g><g v="sing"></g><g v="3per"></g><g v="pres"></g><g v="indc"></g></l></v></tfr></token><token text="долей" id="873046"><tfr t="долей" rev_id="3676916"><v><l t="доля" id="88151"><g v="NOUN"></g><g v="inan"></g><g v="femn"></g><g v="sing"></g><g v="ablt"></g></l></v></tfr></token><token text="в" id="873047"><tfr t="в" rev_id="1752576"><v><l t="в" id="37409"><g v="PREP"></g></l></v></tfr></token><token text="праве" id="873048"><tfr t="праве" rev_id="1752577"><v><l t="право" id="265680"><g v="NOUN"></g><g v="inan"></g><g v="neut"></g><g v="sing"></g><g v="loct"></g></l></v></tfr></token><token text="общей" id="873049"><tfr t="общей" rev_id="4346501"><v><l t="общий" id="201663"><g v="ADJF"></g><g v="femn"></g><g v="sing"></g><g v="gent"></g></l></v></tfr></token><token text="собственности" id="873050"><tfr t="собственности" rev_id="3528676"><v><l t="собственность" id="327839"><g v="NOUN"></g><g v="inan"></g><g v="femn"></g><g v="sing"></g><g v="gent"></g></l></v><v><l t="собственность" id="327839"><g v="NOUN"></g><g v="inan"></g><g v="femn"></g><g v="sing"></g><g v="datv"></g></l></v><v><l t="собственность" id="327839"><g v="NOUN"></g><g v="inan"></g><g v="femn"></g><g v="sing"></g><g v="loct"></g></l></v></tfr></token><token text="на" id="873051"><tfr t="на" rev_id="3338091"><v><l t="на" id="166264"><g v="PREP"></g></l></v></tfr></token><token text="общее" id="873052"><tfr t="общее" rev_id="3812243"><v><l t="общий" id="201663"><g v="ADJF"></g><g v="neut"></g><g v="sing"></g><g v="nomn"></g></l></v><v><l t="общий" id="201663"><g v="ADJF"></g><g v="neut"></g><g v="sing"></g><g v="accs"></g></l></v></tfr></token><token text="имущество" id="873053"><tfr t="имущество" rev_id="4381051"><v><l t="имущество" id="121943"><g v="NOUN"></g><g v="inan"></g><g v="neut"></g><g v="sing"></g><g v="accs"></g></l></v></tfr></token><token text="в" id="873054"><tfr t="в" rev_id="1752583"><v><l t="в" id="37409"><g v="PREP"></g></l></v></tfr></token><token text="данной" id="873055"><tfr t="данной" rev_id="3663298"><v><l t="данна" id="78298"><g v="NOUN"></g><g v="anim"></g><g v="femn"></g><g v="Name"></g><g v="sing"></g><g v="ablt"></g></l></v><v><l t="данный" id="78303"><g v="ADJF"></g><g v="Apro"></g><g v="femn"></g><g v="sing"></g><g v="gent"></g></l></v><v><l t="данный" id="78303"><g v="ADJF"></g><g v="Apro"></g><g v="femn"></g><g v="sing"></g><g v="datv"></g></l></v><v><l t="данный" id="78303"><g v="ADJF"></g><g v="Apro"></g><g v="femn"></g><g v="sing"></g><g v="ablt"></g></l></v><v><l t="данный" id="78303"><g v="ADJF"></g><g v="Apro"></g><g v="femn"></g><g v="sing"></g><g v="loct"></g></l></v><v><l t="данный" id="78549"><g v="PRTF"></g><g v="perf"></g><g v="tran"></g><g v="past"></g><g v="pssv"></g><g v="femn"></g><g v="sing"></g><g v="gent"></g></l></v><v><l t="данный" id="78549"><g v="PRTF"></g><g v="perf"></g><g v="tran"></g><g v="past"></g><g v="pssv"></g><g v="femn"></g><g v="sing"></g><g v="datv"></g></l></v><v><l t="данный" id="78549"><g v="PRTF"></g><g v="perf"></g><g v="tran"></g><g v="past"></g><g v="pssv"></g><g v="femn"></g><g v="sing"></g><g v="ablt"></g></l></v><v><l t="данный" id="78549"><g v="PRTF"></g><g v="perf"></g><g v="tran"></g><g v="past"></g><g v="pssv"></g><g v="femn"></g><g v="sing"></g><g v="loct"></g></l></v></tfr></token><token text="квартире" id="873056"><tfr t="квартире" rev_id="3644803"><v><l t="квартира" id="132025"><g v="NOUN"></g><g v="inan"></g><g v="femn"></g><g v="sing"></g><g v="loct"></g></l></v></tfr></token><token text="указанного" id="873057"><tfr t="указанного" rev_id="4348036"><v><l t="указанный" id="355917"><g v="ADJF"></g><g v="masc"></g><g v="sing"></g><g v="gent"></g></l></v><v><l t="указанный" id="355917"><g v="ADJF"></g><g v="anim"></g><g v="masc"></g><g v="sing"></g><g v="accs"></g></l></v><v><l t="указанный" id="355917"><g v="ADJF"></g><g v="neut"></g><g v="sing"></g><g v="gent"></g></l></v><v><l t="указанный" id="355927"><g v="PRTF"></g><g v="perf"></g><g v="tran"></g><g v="past"></g><g v="pssv"></g><g v="masc"></g><g v="sing"></g><g v="gent"></g></l></v><v><l t="указанный" id="355927"><g v="PRTF"></g><g v="perf"></g><g v="tran"></g><g v="past"></g><g v="pssv"></g><g v="anim"></g><g v="masc"></g><g v="sing"></g><g v="accs"></g></l></v><v><l t="указанный" id="355927"><g v="PRTF"></g><g v="perf"></g><g v="tran"></g><g v="past"></g><g v="pssv"></g><g v="neut"></g><g v="sing"></g><g v="gent"></g></l></v></tfr></token><token text="собственника" id="873058"><tfr t="собственника" rev_id="4359557"><v><l t="собственник" id="327827"><g v="NOUN"></g><g v="anim"></g><g v="masc"></g><g v="sing"></g><g v="gent"></g></l></v></tfr></token><token text="." id="873059"><tfr t="." rev_id="1752588"><v><l t="." id="0"><g v="PNCT"></g></l></v></tfr></token></tokens></sentence></paragraph></paragraphs></text>