<?xml version="1.0" encoding="utf-8"?><text name="129148 кто на новенького?" parent="600" id="2589"><tags><tag>url:http://mashenic.livejournal.com/129148.html</tag></tags><paragraphs><paragraph id="22358"><sentence id="66348"><source>кто на новенького?</source><tokens><token text="кто" id="1207638"><tfr t="кто" rev_id="2834408"><v><l t="кто" id="144216"><g v="NPRO"></g><g v="masc"></g><g v="sing"></g><g v="nomn"></g></l></v></tfr></token><token text="на" id="1207639"><tfr t="на" rev_id="3331241"><v><l t="на" id="166264"><g v="PREP"></g></l></v></tfr></token><token text="новенького" id="1207640"><tfr t="новенького" rev_id="4375556"><v><l t="новенький" id="191499"><g v="ADJF"></g><g v="Subx"></g><g v="masc"></g><g v="sing"></g><g v="gent"></g></l></v><v><l t="новенький" id="191499"><g v="ADJF"></g><g v="Subx"></g><g v="anim"></g><g v="masc"></g><g v="sing"></g><g v="accs"></g></l></v></tfr></token><token text="?" id="1207641"><tfr t="?" rev_id="2834411"><v><l t="?" id="0"><g v="PNCT"></g></l></v></tfr></token></tokens></sentence></paragraph><paragraph id="22359"><sentence id="66349"><source>Обнаружила, что меня читают 48 невзаимных френдов.</source><tokens><token text="Обнаружила" id="1207642"><tfr t="Обнаружила" rev_id="2834412"><v><l t="обнаружил" id="197779"><g v="VERB"></g><g v="perf"></g><g v="tran"></g><g v="femn"></g><g v="sing"></g><g v="past"></g><g v="indc"></g></l></v></tfr></token><token text="," id="1207643"><tfr t="," rev_id="2834413"><v><l t="," id="0"><g v="PNCT"></g></l></v></tfr></token><token text="что" id="1207644"><tfr t="что" rev_id="3201423"><v><l t="что" id="377004"><g v="CONJ"></g></l></v><v><l t="что" id="377005"><g v="NPRO"></g><g v="neut"></g><g v="sing"></g><g v="nomn"></g></l></v><v><l t="что" id="377005"><g v="NPRO"></g><g v="neut"></g><g v="sing"></g><g v="accs"></g></l></v><v><l t="что" id="377006"><g v="ADVB"></g><g v="Ques"></g></l></v><v><l t="что" id="388695"><g v="PRCL"></g></l></v></tfr></token><token text="меня" id="1207645"><tfr t="меня" rev_id="4350999"><v><l t="я" id="387317"><g v="NPRO"></g><g v="1per"></g><g v="sing"></g><g v="accs"></g></l></v></tfr></token><token text="читают" id="1207646"><tfr t="читают" rev_id="2834416"><v><l t="читаю" id="376719"><g v="VERB"></g><g v="impf"></g><g v="tran"></g><g v="plur"></g><g v="3per"></g><g v="pres"></g><g v="indc"></g></l></v></tfr></token><token text="48" id="1207647"><tfr t="48" rev_id="2834417"><v><l t="48" id="0"><g v="NUMB"></g></l></v></tfr></token><token text="невзаимных" id="1207648"><tfr t="невзаимных" rev_id="2834418"><v><l t="невзаимный" id="179721"><g v="ADJF"></g><g v="plur"></g><g v="gent"></g></l></v><v><l t="невзаимный" id="179721"><g v="ADJF"></g><g v="anim"></g><g v="plur"></g><g v="accs"></g></l></v><v><l t="невзаимный" id="179721"><g v="ADJF"></g><g v="plur"></g><g v="loct"></g></l></v></tfr></token><token text="френдов" id="1207649"><tfr t="френдов" rev_id="4384708"><v><l t="френд" id="388807"><g v="NOUN"></g><g v="anim"></g><g v="masc"></g><g v="Slng"></g><g v="plur"></g><g v="gent"></g></l></v></tfr></token><token text="." id="1207650"><tfr t="." rev_id="2834420"><v><l t="." id="0"><g v="PNCT"></g></l></v></tfr></token></tokens></sentence><sentence id="66350"><source>Люди, вы кто =))?</source><tokens><token text="Люди" id="1207651"><tfr t="Люди" rev_id="2834421"><v><l t="человек" id="375073"><g v="NOUN"></g><g v="anim"></g><g v="masc"></g><g v="plur"></g><g v="nomn"></g></l></v></tfr></token><token text="," id="1207652"><tfr t="," rev_id="2834422"><v><l t="," id="0"><g v="PNCT"></g></l></v></tfr></token><token text="вы" id="1207653"><tfr t="вы" rev_id="2834423"><v><l t="вы" id="55560"><g v="NPRO"></g><g v="2per"></g><g v="plur"></g><g v="nomn"></g></l></v></tfr></token><token text="кто" id="1207654"><tfr t="кто" rev_id="2834424"><v><l t="кто" id="144216"><g v="NPRO"></g><g v="masc"></g><g v="sing"></g><g v="nomn"></g></l></v></tfr></token><token text="=))" id="1207655"><tfr t="=))" rev_id="4335639"><v><l t="=))" id="0"><g v="PNCT"></g></l></v></tfr></token><token text="?" id="1207656"><tfr t="?" rev_id="2834426"><v><l t="?" id="0"><g v="PNCT"></g></l></v></tfr></token></tokens></sentence><sentence id="66351"><source>Поскольку вы не комментируете, то я вас не знаю.</source><tokens><token text="Поскольку" id="1207657"><tfr t="Поскольку" rev_id="2834427"><v><l t="поскольку" id="261429"><g v="CONJ"></g></l></v></tfr></token><token text="вы" id="1207658"><tfr t="вы" rev_id="2834428"><v><l t="вы" id="55560"><g v="NPRO"></g><g v="2per"></g><g v="plur"></g><g v="nomn"></g></l></v></tfr></token><token text="не" id="1207659"><tfr t="не" rev_id="2834429"><v><l t="не" id="178876"><g v="PRCL"></g></l></v></tfr></token><token text="комментируете" id="1207660"><tfr t="комментируете" rev_id="2834430"><v><l t="комментирую" id="136976"><g v="VERB"></g><g v="impf"></g><g v="tran"></g><g v="plur"></g><g v="2per"></g><g v="pres"></g><g v="indc"></g></l></v></tfr></token><token text="," id="1207661"><tfr t="," rev_id="2834431"><v><l t="," id="0"><g v="PNCT"></g></l></v></tfr></token><token text="то" id="1207662"><tfr t="то" rev_id="3778747"><v><l t="то" id="346835"><g v="CONJ"></g></l></v><v><l t="то" id="346836"><g v="PRCL"></g></l></v><v><l t="тот" id="348430"><g v="ADJF"></g><g v="Subx"></g><g v="Apro"></g><g v="Anph"></g><g v="neut"></g><g v="sing"></g><g v="nomn"></g></l></v><v><l t="тот" id="348430"><g v="ADJF"></g><g v="Subx"></g><g v="Apro"></g><g v="Anph"></g><g v="neut"></g><g v="sing"></g><g v="accs"></g></l></v></tfr></token><token text="я" id="1207663"><tfr t="я" rev_id="2834433"><v><l t="я" id="387317"><g v="NPRO"></g><g v="1per"></g><g v="sing"></g><g v="nomn"></g></l></v></tfr></token><token text="вас" id="1207664"><tfr t="вас" rev_id="2834434"><v><l t="вы" id="55560"><g v="NPRO"></g><g v="2per"></g><g v="plur"></g><g v="gent"></g></l></v><v><l t="вы" id="55560"><g v="NPRO"></g><g v="2per"></g><g v="plur"></g><g v="accs"></g></l></v><v><l t="вы" id="55560"><g v="NPRO"></g><g v="2per"></g><g v="plur"></g><g v="loct"></g></l></v></tfr></token><token text="не" id="1207665"><tfr t="не" rev_id="2834435"><v><l t="не" id="178876"><g v="PRCL"></g></l></v></tfr></token><token text="знаю" id="1207666"><tfr t="знаю" rev_id="2834436"><v><l t="знаю" id="115989"><g v="VERB"></g><g v="impf"></g><g v="tran"></g><g v="sing"></g><g v="1per"></g><g v="pres"></g><g v="indc"></g></l></v></tfr></token><token text="." id="1207667"><tfr t="." rev_id="2834437"><v><l t="." id="0"><g v="PNCT"></g></l></v></tfr></token></tokens></sentence><sentence id="66352"><source>А может, это большое упущение с моей стороны?</source><tokens><token text="А" id="1207668"><tfr t="А" rev_id="3704181"><v><l t="а" id="51"><g v="CONJ"></g></l></v></tfr></token><token text="может" id="1207669"><tfr t="может" rev_id="4233603"><v><l t="может" id="162457"><g v="CONJ"></g><g v="Prnt"></g></l></v></tfr></token><token text="," id="1207670"><tfr t="," rev_id="2834440"><v><l t="," id="0"><g v="PNCT"></g></l></v></tfr></token><token text="это" id="1207671"><tfr t="это" rev_id="4443278"><v><l t="это" id="386574"><g v="PRCL"></g></l></v><v><l t="это" id="386575"><g v="NPRO"></g><g v="neut"></g><g v="sing"></g><g v="nomn"></g></l></v><v><l t="это" id="386575"><g v="NPRO"></g><g v="neut"></g><g v="sing"></g><g v="accs"></g></l></v><v><l t="этот" id="386581"><g v="ADJF"></g><g v="Subx"></g><g v="Apro"></g><g v="Anph"></g><g v="neut"></g><g v="sing"></g><g v="nomn"></g></l></v><v><l t="этот" id="386581"><g v="ADJF"></g><g v="Subx"></g><g v="Apro"></g><g v="Anph"></g><g v="neut"></g><g v="sing"></g><g v="accs"></g></l></v></tfr></token><token text="большое" id="1207672"><tfr t="большое" rev_id="2834442"><v><l t="большой" id="32445"><g v="ADJF"></g><g v="Qual"></g><g v="neut"></g><g v="sing"></g><g v="nomn"></g></l></v><v><l t="большой" id="32445"><g v="ADJF"></g><g v="Qual"></g><g v="neut"></g><g v="sing"></g><g v="accs"></g></l></v></tfr></token><token text="упущение" id="1207673"><tfr t="упущение" rev_id="4076046"><v><l t="упущение" id="359556"><g v="NOUN"></g><g v="inan"></g><g v="neut"></g><g v="sing"></g><g v="nomn"></g></l></v></tfr></token><token text="с" id="1207674"><tfr t="с" rev_id="2834444"><v><l t="с" id="311151"><g v="PREP"></g></l></v></tfr></token><token text="моей" id="1207675"><tfr t="моей" rev_id="4298608"><v><l t="мой" id="162570"><g v="ADJF"></g><g v="Apro"></g><g v="femn"></g><g v="sing"></g><g v="gent"></g></l></v></tfr></token><token text="стороны" id="1207676"><tfr t="стороны" rev_id="4105114"><v><l t="сторона" id="336894"><g v="NOUN"></g><g v="inan"></g><g v="femn"></g><g v="sing"></g><g v="gent"></g></l></v></tfr></token><token text="?" id="1207677"><tfr t="?" rev_id="2834447"><v><l t="?" id="0"><g v="PNCT"></g></l></v></tfr></token></tokens></sentence><sentence id="66353"><source>Кто хочет быть взаимно зафренженным, отзовитесь =))</source><tokens><token text="Кто" id="1207678"><tfr t="Кто" rev_id="2834448"><v><l t="кто" id="144216"><g v="NPRO"></g><g v="masc"></g><g v="sing"></g><g v="nomn"></g></l></v></tfr></token><token text="хочет" id="1207679"><tfr t="хочет" rev_id="2834449"><v><l t="хочу" id="371713"><g v="VERB"></g><g v="impf"></g><g v="tran"></g><g v="sing"></g><g v="3per"></g><g v="pres"></g><g v="indc"></g></l></v></tfr></token><token text="быть" id="1207680"><tfr t="быть" rev_id="2834450"><v><l t="быть" id="37266"><g v="INFN"></g><g v="impf"></g><g v="intr"></g></l></v></tfr></token><token text="взаимно" id="1207681"><tfr t="взаимно" rev_id="2834451"><v><l t="взаимно" id="42594"><g v="ADVB"></g></l></v><v><l t="взаимен" id="42601"><g v="ADJS"></g><g v="Qual"></g><g v="neut"></g><g v="sing"></g></l></v></tfr></token><token text="зафренженным" id="1207682"><tfr t="зафренженным" rev_id="2834452"><v><l t="зафренженным" id="0"><g v="UNKN"></g></l></v></tfr></token><token text="," id="1207683"><tfr t="," rev_id="2834453"><v><l t="," id="0"><g v="PNCT"></g></l></v></tfr></token><token text="отзовитесь" id="1207684"><tfr t="отзовитесь" rev_id="2834454"><v><l t="отозвался" id="216150"><g v="VERB"></g><g v="perf"></g><g v="intr"></g><g v="plur"></g><g v="impr"></g><g v="excl"></g></l></v></tfr></token><token text="=))" id="1207685"><tfr t="=))" rev_id="4335640"><v><l t="=))" id="0"><g v="PNCT"></g></l></v></tfr></token></tokens></sentence></paragraph></paragraphs></text>