<?xml version="1.0" encoding="utf-8"?><text name="027936" parent="606" id="2719"><tags><tag>url:http://dours.livejournal.com/27936.html</tag></tags><paragraphs><paragraph id="22949"><sentence id="67803"><source>вот люди часто по аське имена людей с маленькой буквы пишут.</source><tokens><token text="вот" id="1230351"><tfr t="вот" rev_id="2858314"><v><l t="вот" id="52157"><g v="PRCL"></g></l></v></tfr></token><token text="люди" id="1230352"><tfr t="люди" rev_id="2858315"><v><l t="человек" id="375073"><g v="NOUN"></g><g v="anim"></g><g v="masc"></g><g v="plur"></g><g v="nomn"></g></l></v></tfr></token><token text="часто" id="1230353"><tfr t="часто" rev_id="2858316"><v><l t="часто" id="374798"><g v="ADVB"></g></l></v><v><l t="част" id="374818"><g v="ADJS"></g><g v="Qual"></g><g v="neut"></g><g v="sing"></g></l></v></tfr></token><token text="по" id="1230354"><tfr t="по" rev_id="2858317"><v><l t="по" id="241240"><g v="PREP"></g></l></v></tfr></token><token text="аське" id="1230355"><tfr t="аське" rev_id="4456477"><v><l t="аська" id="390706"><g v="NOUN"></g><g v="inan"></g><g v="femn"></g><g v="Infr"></g><g v="sing"></g><g v="datv"></g></l></v><v><l t="аська" id="390706"><g v="NOUN"></g><g v="inan"></g><g v="femn"></g><g v="Infr"></g><g v="sing"></g><g v="loct"></g></l></v></tfr></token><token text="имена" id="1230356"><tfr t="имена" rev_id="3763242"><v><l t="имя" id="121947"><g v="NOUN"></g><g v="inan"></g><g v="neut"></g><g v="plur"></g><g v="accs"></g></l></v></tfr></token><token text="людей" id="1230357"><tfr t="людей" rev_id="3660608"><v><l t="человек" id="375073"><g v="NOUN"></g><g v="anim"></g><g v="masc"></g><g v="plur"></g><g v="gent"></g></l></v></tfr></token><token text="с" id="1230358"><tfr t="с" rev_id="2858321"><v><l t="с" id="311151"><g v="PREP"></g></l></v></tfr></token><token text="маленькой" id="1230359"><tfr t="маленькой" rev_id="4404181"><v><l t="маленький" id="153694"><g v="ADJF"></g><g v="Qual"></g><g v="femn"></g><g v="sing"></g><g v="gent"></g></l></v></tfr></token><token text="буквы" id="1230360"><tfr t="буквы" rev_id="3946122"><v><l t="буква" id="35363"><g v="NOUN"></g><g v="inan"></g><g v="femn"></g><g v="sing"></g><g v="gent"></g></l></v></tfr></token><token text="пишут" id="1230361"><tfr t="пишут" rev_id="2858324"><v><l t="пишу" id="239101"><g v="VERB"></g><g v="impf"></g><g v="tran"></g><g v="plur"></g><g v="3per"></g><g v="pres"></g><g v="indc"></g></l></v></tfr></token><token text="." id="1230362"><tfr t="." rev_id="2858325"><v><l t="." id="0"><g v="PNCT"></g></l></v></tfr></token></tokens></sentence><sentence id="67804"><source>а до меня наконец доперло, в какой фразе это важно:</source><tokens><token text="а" id="1230363"><tfr t="а" rev_id="3704188"><v><l t="а" id="51"><g v="CONJ"></g></l></v></tfr></token><token text="до" id="1230364"><tfr t="до" rev_id="2858327"><v><l t="до" id="85153"><g v="PREP"></g></l></v></tfr></token><token text="меня" id="1230365"><tfr t="меня" rev_id="2858328"><v><l t="я" id="387317"><g v="NPRO"></g><g v="1per"></g><g v="sing"></g><g v="gent"></g></l></v><v><l t="я" id="387317"><g v="NPRO"></g><g v="1per"></g><g v="sing"></g><g v="accs"></g></l></v></tfr></token><token text="наконец" id="1230366"><tfr t="наконец" rev_id="2858329"><v><l t="наконец" id="171303"><g v="ADVB"></g></l></v><v><l t="наконец" id="171304"><g v="CONJ"></g><g v="Prnt"></g></l></v></tfr></token><token text="доперло" id="1230367"><tfr t="доперло" rev_id="2858330"><v><l t="допёр" id="89042"><g v="VERB"></g><g v="perf"></g><g v="tran"></g><g v="neut"></g><g v="sing"></g><g v="past"></g><g v="indc"></g></l></v></tfr></token><token text="," id="1230368"><tfr t="," rev_id="2858331"><v><l t="," id="0"><g v="PNCT"></g></l></v></tfr></token><token text="в" id="1230369"><tfr t="в" rev_id="2858332"><v><l t="в" id="37409"><g v="PREP"></g></l></v></tfr></token><token text="какой" id="1230370"><tfr t="какой" rev_id="4380541"><v><l t="какой" id="128224"><g v="ADJF"></g><g v="Apro"></g><g v="femn"></g><g v="sing"></g><g v="loct"></g></l></v></tfr></token><token text="фразе" id="1230371"><tfr t="фразе" rev_id="3660410"><v><l t="фраза" id="367878"><g v="NOUN"></g><g v="inan"></g><g v="femn"></g><g v="sing"></g><g v="loct"></g></l></v></tfr></token><token text="это" id="1230372"><tfr t="это" rev_id="4443409"><v><l t="это" id="386574"><g v="PRCL"></g></l></v><v><l t="это" id="386575"><g v="NPRO"></g><g v="neut"></g><g v="sing"></g><g v="nomn"></g></l></v><v><l t="это" id="386575"><g v="NPRO"></g><g v="neut"></g><g v="sing"></g><g v="accs"></g></l></v><v><l t="этот" id="386581"><g v="ADJF"></g><g v="Subx"></g><g v="Apro"></g><g v="Anph"></g><g v="neut"></g><g v="sing"></g><g v="nomn"></g></l></v><v><l t="этот" id="386581"><g v="ADJF"></g><g v="Subx"></g><g v="Apro"></g><g v="Anph"></g><g v="neut"></g><g v="sing"></g><g v="accs"></g></l></v></tfr></token><token text="важно" id="1230373"><tfr t="важно" rev_id="2858336"><v><l t="важно" id="37717"><g v="ADVB"></g><g v="Prdx"></g></l></v><v><l t="важен" id="37725"><g v="ADJS"></g><g v="Qual"></g><g v="neut"></g><g v="sing"></g></l></v></tfr></token><token text=":" id="1230374"><tfr t=":" rev_id="2858337"><v><l t=":" id="0"><g v="PNCT"></g></l></v></tfr></token></tokens></sentence></paragraph><paragraph id="22950"><sentence id="67805"><source>"Петя любит петь"</source><tokens><token text="&quot;" id="1230375"><tfr t="&quot;" rev_id="2858338"><v><l t="&quot;" id="0"><g v="PNCT"></g></l></v></tfr></token><token text="Петя" id="1230376"><tfr t="Петя" rev_id="2858339"><v><l t="петя" id="238138"><g v="NOUN"></g><g v="anim"></g><g v="masc"></g><g v="Name"></g><g v="sing"></g><g v="nomn"></g></l></v></tfr></token><token text="любит" id="1230377"><tfr t="любит" rev_id="2858340"><v><l t="люблю" id="151971"><g v="VERB"></g><g v="impf"></g><g v="tran"></g><g v="sing"></g><g v="3per"></g><g v="pres"></g><g v="indc"></g></l></v></tfr></token><token text="петь" id="1230378"><tfr t="петь" rev_id="3047961"><v><l t="петь" id="238126"><g v="INFN"></g><g v="impf"></g><g v="tran"></g></l></v></tfr></token><token text="&quot;" id="1230379"><tfr t="&quot;" rev_id="2858342"><v><l t="&quot;" id="0"><g v="PNCT"></g></l></v></tfr></token></tokens></sentence></paragraph><paragraph id="22951"><sentence id="67806"><source>и</source><tokens><token text="и" id="1230380"><tfr t="и" rev_id="2858343"><v><l t="и" id="116949"><g v="CONJ"></g></l></v><v><l t="и" id="116950"><g v="INTJ"></g></l></v></tfr></token></tokens></sentence></paragraph><paragraph id="22952"><sentence id="67807"><source>"Петя любит Петь"--- не одно и то же</source><tokens><token text="&quot;" id="1230381"><tfr t="&quot;" rev_id="2858344"><v><l t="&quot;" id="0"><g v="PNCT"></g></l></v></tfr></token><token text="Петя" id="1230382"><tfr t="Петя" rev_id="2858345"><v><l t="петя" id="238138"><g v="NOUN"></g><g v="anim"></g><g v="masc"></g><g v="Name"></g><g v="sing"></g><g v="nomn"></g></l></v></tfr></token><token text="любит" id="1230383"><tfr t="любит" rev_id="2858346"><v><l t="люблю" id="151971"><g v="VERB"></g><g v="impf"></g><g v="tran"></g><g v="sing"></g><g v="3per"></g><g v="pres"></g><g v="indc"></g></l></v></tfr></token><token text="Петь" id="1230384"><tfr t="Петь" rev_id="4384589"><v><l t="петя" id="238138"><g v="NOUN"></g><g v="anim"></g><g v="masc"></g><g v="Name"></g><g v="plur"></g><g v="accs"></g></l></v></tfr></token><token text="&quot;" id="1230385"><tfr t="&quot;" rev_id="2858348"><v><l t="&quot;" id="0"><g v="PNCT"></g></l></v></tfr></token><token text="---" id="1230386"><tfr t="---" rev_id="2858349"><v><l t="---" id="0"><g v="PNCT"></g></l></v></tfr></token><token text="не" id="1230387"><tfr t="не" rev_id="2858350"><v><l t="не" id="178876"><g v="PRCL"></g></l></v></tfr></token><token text="одно" id="1230388"><tfr t="одно" rev_id="4303176"><v><l t="один" id="203319"><g v="ADJF"></g><g v="Apro"></g><g v="Anum"></g><g v="neut"></g><g v="sing"></g><g v="nomn"></g></l></v><v><l t="один" id="203319"><g v="ADJF"></g><g v="Apro"></g><g v="Anum"></g><g v="neut"></g><g v="sing"></g><g v="accs"></g></l></v></tfr></token><token text="и" id="1230389"><tfr t="и" rev_id="2858352"><v><l t="и" id="116949"><g v="CONJ"></g></l></v><v><l t="и" id="116950"><g v="INTJ"></g></l></v></tfr></token><token text="то" id="1230390"><tfr t="то" rev_id="3778831"><v><l t="то" id="346835"><g v="CONJ"></g></l></v><v><l t="то" id="346836"><g v="PRCL"></g></l></v><v><l t="тот" id="348430"><g v="ADJF"></g><g v="Subx"></g><g v="Apro"></g><g v="Anph"></g><g v="neut"></g><g v="sing"></g><g v="nomn"></g></l></v><v><l t="тот" id="348430"><g v="ADJF"></g><g v="Subx"></g><g v="Apro"></g><g v="Anph"></g><g v="neut"></g><g v="sing"></g><g v="accs"></g></l></v></tfr></token><token text="же" id="1230391"><tfr t="же" rev_id="2858354"><v><l t="же" id="96208"><g v="CONJ"></g></l></v><v><l t="же" id="96209"><g v="PRCL"></g></l></v></tfr></token></tokens></sentence></paragraph></paragraphs></text>